Workbook

Sheet Estimate
A1: ESTIMATE — this job
A2: Fill the white columns. The corrected column applies what you learned from past jobs.
A4: Phase | B4: Your estimate | C4: Correction factor (from your last job) | D4: Corrected estimate | E4: Notes
A5: Pre-construction & permits | C5: 1 | D5: =IF(N(B5)=0,0,B5*IF(N(C5)=0,1,C5))
A6: Site protection & logistics | C6: 1 | D6: =IF(N(B6)=0,0,B6*IF(N(C6)=0,1,C6))
A7: Demolition & disposal | C7: 1 | D7: =IF(N(B7)=0,0,B7*IF(N(C7)=0,1,C7))
A8: Structural & framing | C8: 1 | D8: =IF(N(B8)=0,0,B8*IF(N(C8)=0,1,C8))
A9: Plumbing | C9: 1 | D9: =IF(N(B9)=0,0,B9*IF(N(C9)=0,1,C9))
A10: Electrical | C10: 1 | D10: =IF(N(B10)=0,0,B10*IF(N(C10)=0,1,C10))
A11: HVAC | C11: 1 | D11: =IF(N(B11)=0,0,B11*IF(N(C11)=0,1,C11))
A12: Insulation & drywall | C12: 1 | D12: =IF(N(B12)=0,0,B12*IF(N(C12)=0,1,C12))
A13: Flooring & tile | C13: 1 | D13: =IF(N(B13)=0,0,B13*IF(N(C13)=0,1,C13))
A14: Cabinets & countertops | C14: 1 | D14: =IF(N(B14)=0,0,B14*IF(N(C14)=0,1,C14))
A15: Trim, doors & hardware | C15: 1 | D15: =IF(N(B15)=0,0,B15*IF(N(C15)=0,1,C15))
A16: Paint | C16: 1 | D16: =IF(N(B16)=0,0,B16*IF(N(C16)=0,1,C16))
... A19: Clean, punch & closeout | C19: 1 | D19: =IF(N(B19)=0,0,B19*IF(N(C19)=0,1,C19))
A20: TOTAL DIRECT COST | B20: =SUM(B5:B19) | D20: =SUM(D5:D19)
A22: Overhead & profit markup | B22: 0.2
A23: BID PRICE | B23: =D20*(1+B22)
A25: Markup is not profit. It has to cover overhead first — see the guide.
A26: The shaded factor column is yours to type in: copy it from the Variance tab of your LAST job. On job one, leave every factor at 1.00 — you have no history yet, and pretending otherwise is guessing.

Sheet Actuals
A1: ACTUALS — what it really cost
A2: Fill this at closeout, while you still remember. This is the only input that makes the kit work.
A4: Phase | B4: Actual cost | C4: What drove the difference | D4: Was it price or scope?
A5: Pre-construction & permits
A6: Site protection & logistics
A7: Demolition & disposal
A8: Structural & framing
A9: Plumbing
A10: Electrical
A11: HVAC
A12: Insulation & drywall
A13: Flooring & tile
A14: Cabinets & countertops
A15: Trim, doors & hardware
A16: Paint
... A19: Clean, punch & closeout
A20: TOTAL ACTUAL | B20: =SUM(B5:B19)

Sheet Variance & Factors
A1: VARIANCE & CORRECTION FACTORS
A2: Nothing to fill here. Read it. The factor column feeds back into the Estimate tab automatically.
A4: Phase | B4: Estimated | C4: Actual | D4: Variance | E4: Correction factor | F4: Read this as
A5: Pre-construction & permits | B5: =Estimate!B5 | C5: =Actuals!B5 | D5: =IF(N(B5)=0,"",C5-B5) | E5: =IF(OR(N(B5)=0,N(C5)=0),1,ROUND(C5/B5,2)) | F5: =IF(OR(N(B5)=0,N(C5)=0),"add this job's numbers",IF(E5>1.1,"you underprice this phase — the factor now corrects it",IF(E5<0.9,"you pad this phase — you may be losing bids on it","this phase is under control")))
A6: Site protection & logistics | B6: =Estimate!B6 | C6: =Actuals!B6 | D6: =IF(N(B6)=0,"",C6-B6) | E6: =IF(OR(N(B6)=0,N(C6)=0),1,ROUND(C6/B6,2)) | F6: =IF(OR(N(B6)=0,N(C6)=0),"add this job's numbers",IF(E6>1.1,"you underprice this phase — the factor now corrects it",IF(E6<0.9,"you pad this phase — you may be losing bids on it","this phase is under control")))
A7: Demolition & disposal | B7: =Estimate!B7 | C7: =Actuals!B7 | D7: =IF(N(B7)=0,"",C7-B7) | E7: =IF(OR(N(B7)=0,N(C7)=0),1,ROUND(C7/B7,2)) | F7: =IF(OR(N(B7)=0,N(C7)=0),"add this job's numbers",IF(E7>1.1,"you underprice this phase — the factor now corrects it",IF(E7<0.9,"you pad this phase — you may be losing bids on it","this phase is under control")))
A8: Structural & framing | B8: =Estimate!B8 | C8: =Actuals!B8 | D8: =IF(N(B8)=0,"",C8-B8) | E8: =IF(OR(N(B8)=0,N(C8)=0),1,ROUND(C8/B8,2)) | F8: =IF(OR(N(B8)=0,N(C8)=0),"add this job's numbers",IF(E8>1.1,"you underprice this phase — the factor now corrects it",IF(E8<0.9,"you pad this phase — you may be losing bids on it","this phase is under control")))
A9: Plumbing | B9: =Estimate!B9 | C9: =Actuals!B9 | D9: =IF(N(B9)=0,"",C9-B9) | E9: =IF(OR(N(B9)=0,N(C9)=0),1,ROUND(C9/B9,2)) | F9: =IF(OR(N(B9)=0,N(C9)=0),"add this job's numbers",IF(E9>1.1,"you underprice this phase — the factor now corrects it",IF(E9<0.9,"you pad this phase — you may be losing bids on it","this phase is under control")))
A10: Electrical | B10: =Estimate!B10 | C10: =Actuals!B10 | D10: =IF(N(B10)=0,"",C10-B10) | E10: =IF(OR(N(B10)=0,N(C10)=0),1,ROUND(C10/B10,2)) | F10: =IF(OR(N(B10)=0,N(C10)=0),"add this job's numbers",IF(E10>1.1,"you underprice this phase — the factor now corrects it",IF(E10<0.9,"you pad this phase — you may be losing bids on it","this phase is under control")))
A11: HVAC | B11: =Estimate!B11 | C11: =Actuals!B11 | D11: =IF(N(B11)=0,"",C11-B11) | E11: =IF(OR(N(B11)=0,N(C11)=0),1,ROUND(C11/B11,2)) | F11: =IF(OR(N(B11)=0,N(C11)=0),"add this job's numbers",IF(E11>1.1,"you underprice this phase — the factor now corrects it",IF(E11<0.9,"you pad this phase — you may be losing bids on it","this phase is under control")))
A12: Insulation & drywall | B12: =Estimate!B12 | C12: =Actuals!B12 | D12: =IF(N(B12)=0,"",C12-B12) | E12: =IF(OR(N(B12)=0,N(C12)=0),1,ROUND(C12/B12,2)) | F12: =IF(OR(N(B12)=0,N(C12)=0),"add this job's numbers",IF(E12>1.1,"you underprice this phase — the factor now corrects it",IF(E12<0.9,"you pad this phase — you may be losing bids on it","this phase is under control")))
A13: Flooring & tile | B13: =Estimate!B13 | C13: =Actuals!B13 | D13: =IF(N(B13)=0,"",C13-B13) | E13: =IF(OR(N(B13)=0,N(C13)=0),1,ROUND(C13/B13,2)) | F13: =IF(OR(N(B13)=0,N(C13)=0),"add this job's numbers",IF(E13>1.1,"you underprice this phase — the factor now corrects it",IF(E13<0.9,"you pad this phase — you may be losing bids on it","this phase is under control")))
A14: Cabinets & countertops | B14: =Estimate!B14 | C14: =Actuals!B14 | D14: =IF(N(B14)=0,"",C14-B14) | E14: =IF(OR(N(B14)=0,N(C14)=0),1,ROUND(C14/B14,2)) | F14: =IF(OR(N(B14)=0,N(C14)=0),"add this job's numbers",IF(E14>1.1,"you underprice this phase — the factor now corrects it",IF(E14<0.9,"you pad this phase — you may be losing bids on it","this phase is under control")))
A15: Trim, doors & hardware | B15: =Estimate!B15 | C15: =Actuals!B15 | D15: =IF(N(B15)=0,"",C15-B15) | E15: =IF(OR(N(B15)=0,N(C15)=0),1,ROUND(C15/B15,2)) | F15: =IF(OR(N(B15)=0,N(C15)=0),"add this job's numbers",IF(E15>1.1,"you underprice this phase — the factor now corrects it",IF(E15<0.9,"you pad this phase — you may be losing bids on it","this phase is under control")))
A16: Paint | B16: =Estimate!B16 | C16: =Actuals!B16 | D16: =IF(N(B16)=0,"",C16-B16) | E16: =IF(OR(N(B16)=0,N(C16)=0),1,ROUND(C16/B16,2)) | F16: =IF(OR(N(B16)=0,N(C16)=0),"add this job's numbers",IF(E16>1.1,"you underprice this phase — the factor now corrects it",IF(E16<0.9,"you pad this phase — you may be losing bids on it","this phase is under control")))
... A19: Clean, punch & closeout | B19: =Estimate!B19 | C19: =Actuals!B19 | D19: =IF(N(B19)=0,"",C19-B19) | E19: =IF(OR(N(B19)=0,N(C19)=0),1,ROUND(C19/B19,2)) | F19: =IF(OR(N(B19)=0,N(C19)=0),"add this job's numbers",IF(E19>1.1,"you underprice this phase — the factor now corrects it",IF(E19<0.9,"you pad this phase — you may be losing bids on it","this phase is under control")))
A20: TOTAL | B20: =SUM(B5:B19) | C20: =SUM(C5:C19) | D20: =C20-B20
A22: One job is an anecdote. Five jobs is your number.
A23: Copy this file per job. After five, the factors stop moving much — that is when they are worth trusting.

Sheet Instructions
A1: HOW TO RUN THE LOOP
A2: Five steps. The whole kit is this.
A5: 1 | B5: Copy this file for the job. Name it with the job name. One file per job — that is the whole filing system.
A7: 2 | B7: Fill the Estimate tab, one number per phase. Use the Missed Line Items Checklist before you call it done.
A9: 3 | B9: Bid the Corrected total, not your raw total — the factors carry what past jobs taught you. On job one there is no history, so the two are the same.
A11: 4 | B11: At closeout, fill the Actuals tab. Write the reason in plain words and mark whether it was price or scope. Do it the week the job ends, not at tax time.
A13: 5 | B13: Read Variance & Factors. Carry the factors into the next job's file. After five jobs they stabilize — that is your number, and nobody else has it.
B16: Price vs. scope matters: if the cost went up because material got more expensive, that is price, and the factor should carry it. If it went up because you did work that was never in the estimate, that is scope, and the fix is the checklist and the change order — not the factor. Marking this wrong is the one way to teach the loop the wrong lesson.
B18: Excel 365 / 2021+. Formulas are visible and unlocked — click any cell and read it. It is your file.
